{
    "accountItems": [
        {
            "destination": "ACCNTNUM",
            "source": "ACCNTNUM"
        },
        {
            "destination": "ACCNTNAME",
            "source": "ACCNTNAME"
        },
        {
            "destination": "USERTXT1",
            "source": "USERTXT1"
        },
        {
            "destination": "POLICYTYPE",
            "source": "POLICYTYPE"
        },
        {
            "destination": "POLICYNUM",
            "source": "POLICYNUM"
        },
        {
            "destination": "CEDANTID",
            "source": "CEDANTID"
        },
        {
            "destination": "CEDANTNAME",
            "source": "CEDANTNAME"
        },
        {
            "destination": "LOBNAME",
            "source": "LOBNAME"
        },
        {
            "destination": "BLANLIMAMT",
            "source": "BLANLIMAMT"
        }
    ],
    "locationItems": [
        {
            "destination": "ACCNTNUM",
            "source": "ACCNTNUM"
        },
        {
            "destination": "LOCNUM",
            "source": "LOCNUM"
        },
        {
            "destination": "LOCNAME",
            "source": "LOCNAME"
        },
        {
            "destination": "CNTRYCODE",
            "source": "CNTRYCODE"
        },
        {
            "destination": "USERTXT1",
            "source": "USERTXT1"
        },
        {
            "destination": "STREETNAME",
            "source": "STREETNAME"
        },
        {
            "destination": "CRESTA",
            "source": "CRESTA"
        },
        {
            "destination": "POSTALCODE",
            "source": "POSTALCODE"
        },
        {
            "destination": "Admin4Name",
            "source": "ADMIN4NAME"
        },
        {
            "destination": "CITY",
            "source": "CITY"
        },
        {
            "destination": "DSTRCTCODE",
            "source": "DSTRCTCODE"
        },
        {
            "destination": "DISTRICT",
            "source": "DISTRICT"
        },
        {
            "destination": "COUNTY",
            "source": "COUNTY"
        },
        {
            "destination": "STATECODE",
            "source": "STATECODE"
        },
        {
            "destination": "STATE",
            "source": "STATE"
        },
        {
            "destination": "LATITUDE",
            "source": "LATITUDE"
        },
        {
            "destination": "LONGITUDE",
            "source": "LONGITUDE"
        },
        {
            "destination": "Zone3Name",
            "source": "ZONE3NAME"
        },
        {
            "destination": "USERGEO1",
            "source": "USERGEO1"
        },
        {
            "destination": "BLDGSCHEME",
            "source": "BLDGSCHEME"
        },
        {
            "destination": "BLDGCLASS",
            "source": "BLDGCLASS"
        },
        {
            "destination": "OCCSCHEME",
            "source": "OCCSCHEME"
        },
        {
            "destination": "OCCTYPE",
            "source": "OCCTYPE"
        },
        {
            "destination": "NUMSTORIES",
            "source": "NUMSTORIES"
        },
        {
            "destination": "CNTRYSCHEME",
            "source": "CNTRYSCHEME"
        },
        {
            "destination": "WSCV1VAL",
            "source": "WSCV1VAL"
        },
        {
            "destination": "WSCV2VAL",
            "source": "WSCV2VAL"
        },
        {
            "destination": "WSCV3VAL",
            "source": "WSCV3VAL"
        },
        {
            "destination": "EQCV1VAL",
            "source": "EQCV1VAL"
        },
        {
            "destination": "EQCV2VAL",
            "source": "EQCV2VAL"
        },
        {
            "destination": "EQCV3VAL",
            "source": "EQCV3VAL"
        },
        {
            "destination": "FLCV1VAL",
            "source": "FLCV1VAL"
        },
        {
            "destination": "FLCV2VAL",
            "source": "FLCV2VAL"
        },
        {
            "destination": "FLCV3VAL",
            "source": "FLCV3VAL"
        },
        {
            "destination": "TOCV1VAL",
            "source": "TOCV1VAL"
        },
        {
            "destination": "TOCV2VAL",
            "source": "TOCV2VAL"
        },
        {
            "destination": "TOCV3VAL",
            "source": "TOCV3VAL"
        },
        {
            "destination": "WSCV1DED",
            "source": "WSCV1DED"
        },
        {
            "destination": "WSCV2DED",
            "source": "WSCV2DED"
        },
        {
            "destination": "WSCV3DED",
            "source": "WSCV3DED"
        },
        {
            "destination": "EQCV1DED",
            "source": "EQCV1DED"
        },
        {
            "destination": "EQCV2DED",
            "source": "EQCV2DED"
        },
        {
            "destination": "EQCV3DED",
            "source": "EQCV3DED"
        },
        {
            "destination": "FLCV1DED",
            "source": "FLCV1DED"
        },
        {
            "destination": "FLCV2DED",
            "source": "FLCV2DED"
        },
        {
            "destination": "FLCV3DED",
            "source": "FLCV3DED"
        },
        {
            "destination": "TOCV1DED",
            "source": "TOCV1DED"
        },
        {
            "destination": "TOCV2DED",
            "source": "TOCV2DED"
        },
        {
            "destination": "TOCV3DED",
            "source": "TOCV3DED"
        },
        {
            "destination": "TRCV1VAL",
            "source": "TRCV1VAL"
        },
        {
            "destination": "TRCV2VAL",
            "source": "TRCV2VAL"
        },
        {
            "destination": "TRCV3VAL",
            "source": "TRCV3VAL"
        },
        {
            "destination": "TRCV1DED",
            "source": "TRCV1DED"
        },
        {
            "destination": "TRCV2DED",
            "source": "TRCV2DED"
        },
        {
            "destination": "TRCV3DED",
            "source": "TRCV3DED"
        }
    ],
    "reinsuranceItems": [],
    "mapFileName": "map1"
}